SmartLift.v
// SmartLift.v — FPGA Elevator FSM Controller
// 8-floor elevator: floors 0–7
// Outputs: idle, door, Up, Down, current_floor, requests, max/min_request
// States: RESET → IDLE → MOVING_UP / MOVING_DOWN → DOOR_OPEN → IDLE
// Emergency stop overrides all motion

module SmartLift #(
    parameter [2:0] START_FLOOR = 3'd0
)(
    input             clk,
    input             reset,
    input      [2:0]  req_floor,
    output reg [1:0]  idle,
    output reg [1:0]  door,
    output reg [1:0]  Up,
    output reg [1:0]  Down,
    output reg [2:0]  current_floor,
    output reg [7:0]  requests,
    output reg [2:0]  max_request,
    output reg [2:0]  min_request,
    input             emergency_stop
);

// FSM state encoding
localparam S_RESET    = 3'd0;
localparam S_IDLE     = 3'd1;
localparam S_MOVE_UP  = 3'd2;
localparam S_MOVE_DN  = 3'd3;
localparam S_DOOR     = 3'd4;
localparam S_EMERG    = 3'd5;

reg [2:0] state;
reg       direction_up;
reg       sampled_req;
reg [2:0] last_req_floor;
reg [2:0] move_wait;
reg [2:0] door_wait;

localparam [2:0] MOVE_TICKS = 3'd2; // cycles per floor movement
localparam [2:0] DOOR_TICKS = 3'd3; // cycles to hold door open

// Returns 1 if any pending request exists above floor f.
function has_above;
    input [2:0] f;
    begin
        case (f)
            3'd0: has_above = |requests[7:1];
            3'd1: has_above = |requests[7:2];
            3'd2: has_above = |requests[7:3];
            3'd3: has_above = |requests[7:4];
            3'd4: has_above = |requests[7:5];
            3'd5: has_above = |requests[7:6];
            3'd6: has_above =  requests[7];
            default: has_above = 1'b0;
        endcase
    end
endfunction

// Returns 1 if any pending request exists below floor f.
function has_below;
    input [2:0] f;
    begin
        case (f)
            3'd0: has_below = 1'b0;
            3'd1: has_below = requests[0];
            3'd2: has_below = |requests[1:0];
            3'd3: has_below = |requests[2:0];
            3'd4: has_below = |requests[3:0];
            3'd5: has_below = |requests[4:0];
            3'd6: has_below = |requests[5:0];
            default: has_below = |requests[6:0];
        endcase
    end
endfunction

always @(posedge clk or posedge reset) begin
    if (reset) begin
        state         <= S_RESET;
        current_floor <= START_FLOOR;
        idle          <= 2'd1;
        door          <= 2'd0;
        Up            <= 2'd1;
        Down          <= 2'd0;
        requests      <= 8'd0;
        max_request   <= START_FLOOR;
        min_request   <= START_FLOOR;
        direction_up  <= 1'b1;
        sampled_req   <= 1'b0;
        last_req_floor<= 3'd0;
        move_wait     <= 3'd0;
        door_wait     <= 3'd0;
    end
    else if (emergency_stop) begin
        state  <= S_EMERG;
        idle   <= 2'd0;
        door   <= 2'd0;
        Up     <= 2'd0;
        Down   <= 2'd0;
    end
    else begin
        // Latch a new button event when req_floor changes.
        // This allows rapid random floor presses to be queued.
        if (!sampled_req) begin
            sampled_req    <= 1'b1;
            last_req_floor <= req_floor;
        end
        else if (req_floor != last_req_floor) begin
            requests[req_floor] <= 1'b1;
            last_req_floor      <= req_floor;
        end

        // Maintain min/max request metadata for display/debug.
        if (requests == 8'd0) begin
            max_request <= current_floor;
            min_request <= current_floor;
        end
        else begin
            if (requests[7]) begin
                max_request <= 3'd7;
            end
            else if (requests[6]) begin
                max_request <= 3'd6;
            end
            else if (requests[5]) begin
                max_request <= 3'd5;
            end
            else if (requests[4]) begin
                max_request <= 3'd4;
            end
            else if (requests[3]) begin
                max_request <= 3'd3;
            end
            else if (requests[2]) begin
                max_request <= 3'd2;
            end
            else if (requests[1]) begin
                max_request <= 3'd1;
            end
            else begin
                max_request <= 3'd0;
            end

            if (requests[0]) begin
                min_request <= 3'd0;
            end
            else if (requests[1]) begin
                min_request <= 3'd1;
            end
            else if (requests[2]) begin
                min_request <= 3'd2;
            end
            else if (requests[3]) begin
                min_request <= 3'd3;
            end
            else if (requests[4]) begin
                min_request <= 3'd4;
            end
            else if (requests[5]) begin
                min_request <= 3'd5;
            end
            else if (requests[6]) begin
                min_request <= 3'd6;
            end
            else begin
                min_request <= 3'd7;
            end
        end

        case (state)
            S_RESET: begin
                state <= S_IDLE;
                idle  <= 2'd1;
            end

            S_IDLE: begin
                if (requests[current_floor]) begin
                    // Serve current floor immediately if pending.
                    requests[current_floor] <= 1'b0;
                    state <= S_DOOR;
                    door  <= 2'd1;
                    idle  <= 2'd1;
                    Up    <= 2'd0;
                    Down  <= 2'd0;
                    door_wait <= 3'd0;
                end
                else if (direction_up && has_above(current_floor)) begin
                    state <= S_MOVE_UP;
                    idle  <= 2'd0;
                    door  <= 2'd0;
                    Up    <= 2'd1;
                    Down  <= 2'd0;
                    move_wait <= 3'd0;
                end
                else if (direction_up && has_below(current_floor)) begin
                    direction_up <= 1'b0;
                    state <= S_MOVE_DN;
                    idle  <= 2'd0;
                    door  <= 2'd0;
                    Up    <= 2'd0;
                    Down  <= 2'd1;
                    move_wait <= 3'd0;
                end
                else if (!direction_up && has_below(current_floor)) begin
                    state <= S_MOVE_DN;
                    idle  <= 2'd0;
                    door  <= 2'd0;
                    Up    <= 2'd0;
                    Down  <= 2'd1;
                    move_wait <= 3'd0;
                end
                else if (!direction_up && has_above(current_floor)) begin
                    direction_up <= 1'b1;
                    state <= S_MOVE_UP;
                    idle  <= 2'd0;
                    door  <= 2'd0;
                    Up    <= 2'd1;
                    Down  <= 2'd0;
                    move_wait <= 3'd0;
                end
                else begin
                    // No pending requests.
                    state <= S_IDLE;
                    idle  <= 2'd1;
                    door  <= 2'd0;
                    Up    <= 2'd0;
                    Down  <= 2'd0;
                end
            end

            S_MOVE_UP: begin
                if (move_wait < (MOVE_TICKS - 1'b1)) begin
                    move_wait <= move_wait + 1'b1;
                end
                else begin
                    move_wait <= 3'd0;
                    if (current_floor < 3'd7) begin
                        current_floor <= current_floor + 1'b1;
                        if (requests[current_floor + 1'b1]) begin
                            requests[current_floor + 1'b1] <= 1'b0;
                            state <= S_DOOR;
                            door  <= 2'd1;
                            Up    <= 2'd0;
                            idle  <= 2'd1;
                            door_wait <= 3'd0;
                        end
                    end
                    else if (has_below(current_floor)) begin
                        direction_up <= 1'b0;
                        state <= S_MOVE_DN;
                        Up    <= 2'd0;
                        Down  <= 2'd1;
                    end
                    else begin
                        state <= S_IDLE;
                        Up    <= 2'd0;
                        idle  <= 2'd1;
                    end
                end
            end

            S_MOVE_DN: begin
                if (move_wait < (MOVE_TICKS - 1'b1)) begin
                    move_wait <= move_wait + 1'b1;
                end
                else begin
                    move_wait <= 3'd0;
                    if (current_floor > 3'd0) begin
                        current_floor <= current_floor - 1'b1;
                        if (requests[current_floor - 1'b1]) begin
                            requests[current_floor - 1'b1] <= 1'b0;
                            state <= S_DOOR;
                            door  <= 2'd1;
                            Down  <= 2'd0;
                            idle  <= 2'd1;
                            door_wait <= 3'd0;
                        end
                    end
                    else if (has_above(current_floor)) begin
                        direction_up <= 1'b1;
                        state <= S_MOVE_UP;
                        Up    <= 2'd1;
                        Down  <= 2'd0;
                    end
                    else begin
                        state <= S_IDLE;
                        Down  <= 2'd0;
                        idle  <= 2'd1;
                    end
                end
            end

            S_DOOR: begin
                // Hold door open for a few cycles to mimic dwell time.
                door <= 2'd1;
                if (door_wait < (DOOR_TICKS - 1'b1)) begin
                    door_wait <= door_wait + 1'b1;
                end
                else begin
                    door_wait <= 3'd0;
                    door  <= 2'd0;
                    state <= S_IDLE;
                end
            end

            S_EMERG: begin
                // Stay halted until reset
                idle  <= 2'd0;
                door  <= 2'd0;
            end
        endcase
    end
end

endmodule

SmartLift_Tb.v
`timescale 1ns/1ps
module SmartLift_Tb();
  reg clk=0, reset=1, emergency_stop=0;
  reg [2:0] req_floor = 0;
  wire [2:0] current_floor;
  wire [1:0] idle, door, Up, Down;
  wire [7:0] requests;
  wire [2:0] max_request, min_request;

  SmartLift #(.START_FLOOR(3'd5)) dut(
    clk, reset, req_floor,
    idle, door, Up, Down,
    current_floor, requests,
    max_request, min_request, emergency_stop
  );

  initial begin
    $dumpfile("waveform.vcd");
    $dumpvars(0, SmartLift_Tb);
    #10 reset = 0;
    #10 req_floor = 4; // Button press for floor 4
    #10 req_floor = 2; // Button press for floor 2
    #10 req_floor = 0; // Button press for floor 0
    #10 req_floor = 6; // Button press for floor 6
    #320 ; // Let controller serve all pending requests
    #20 $finish;
  end

  always #5 clk = ~clk; // 100MHz clock (10ns period)
endmodule

waveform.vcd
$date
	Fri Apr 24 09:48:05 2026
$end
$version
	Icarus Verilog
$end
$timescale
	1ps
$end
$scope module SmartLift_Tb $end
$var wire 8 ! requests [7:0] $end
$var wire 3 " min_request [2:0] $end
$var wire 3 # max_request [2:0] $end
$var wire 2 $ idle [1:0] $end
$var wire 2 % door [1:0] $end
$var wire 3 & current_floor [2:0] $end
$var wire 2 ' Up [1:0] $end
$var wire 2 ( Down [1:0] $end
$var reg 1 ) clk $end
$var reg 1 * emergency_stop $end
$var reg 3 + req_floor [2:0] $end
$var reg 1 , reset $end
$scope module dut $end
$var wire 1 ) clk $end
$var wire 1 * emergency_stop $end
$var wire 3 - req_floor [2:0] $end
$var wire 1 , reset $end
$var parameter 3 . DOOR_TICKS $end
$var parameter 3 / MOVE_TICKS $end
$var parameter 3 0 START_FLOOR $end
$var parameter 3 1 S_DOOR $end
$var parameter 3 2 S_EMERG $end
$var parameter 3 3 S_IDLE $end
$var parameter 3 4 S_MOVE_DN $end
$var parameter 3 5 S_MOVE_UP $end
$var parameter 3 6 S_RESET $end
$var reg 2 7 Down [1:0] $end
$var reg 2 8 Up [1:0] $end
$var reg 3 9 current_floor [2:0] $end
$var reg 1 : direction_up $end
$var reg 2 ; door [1:0] $end
$var reg 3 < door_wait [2:0] $end
$var reg 2 = idle [1:0] $end
$var reg 3 > last_req_floor [2:0] $end
$var reg 3 ? max_request [2:0] $end
$var reg 3 @ min_request [2:0] $end
$var reg 3 A move_wait [2:0] $end
$var reg 8 B requests [7:0] $end
$var reg 1 C sampled_req $end
$var reg 3 D state [2:0] $end
$scope function has_above $end
$var reg 3 E f [2:0] $end
$upscope $end
$scope function has_below $end
$var reg 3 F f [2:0] $end
$upscope $end
$upscope $end
$upscope $end
$enddefinitions $end
$comment Show the parameter values. $end
$dumpall
b0 6
b10 5
b11 4
b1 3
b101 2
b100 1
b101 0
b10 /
b11 .
$end
#0
$dumpvars
bx F
bx E
b0 D
0C
b0 B
b0 A
b101 @
b101 ?
b0 >
b1 =
b0 <
b0 ;
1:
b101 9
b1 8
b0 7
b0 -
1,
b0 +
0*
0)
b0 (
b1 '
b101 &
b0 %
b1 $
b101 #
b101 "
b0 !
$end
#5000
1)
#10000
0)
0,
#15000
b1 D
1C
1)
#20000
0)
b100 +
b100 -
#25000
b0 '
b0 8
b100 >
b10000 !
b10000 B
b101 F
b101 E
1)
#30000
0)
b10 +
b10 -
#35000
b1 (
b1 7
b0 $
b0 =
b11 D
0:
b100 "
b100 @
b100 #
b100 ?
b10 >
b10100 !
b10100 B
1)
#40000
0)
b0 +
b0 -
#45000
b1 A
b10 "
b10 @
b0 >
b10101 !
b10101 B
1)
#50000
0)
b110 +
b110 -
#55000
b1 $
b1 =
b0 (
b0 7
b1 %
b1 ;
b100 D
b100 &
b100 9
b0 A
b0 "
b0 @
b110 >
b1000101 !
b1000101 B
1)
#60000
0)
#65000
b1 <
b110 #
b110 ?
1)
#70000
0)
#75000
b10 <
1)
#80000
0)
#85000
b1 D
b0 %
b0 ;
b0 <
1)
#90000
0)
#95000
b1 (
b1 7
b0 $
b0 =
b11 D
b100 F
1)
#100000
0)
#105000
b1 A
1)
#110000
0)
#115000
b11 &
b11 9
b0 A
1)
#120000
0)
#125000
b1 A
1)
#130000
0)
#135000
b1 $
b1 =
b0 (
b0 7
b1 %
b1 ;
b100 D
b1000001 !
b1000001 B
b10 &
b10 9
b0 A
1)
#140000
0)
#145000
b1 <
1)
#150000
0)
#155000
b10 <
1)
#160000
0)
#165000
b1 D
b0 %
b0 ;
b0 <
1)
#170000
0)
#175000
b1 (
b1 7
b0 $
b0 =
b11 D
b10 F
1)
#180000
0)
#185000
b1 A
1)
#190000
0)
#195000
b1 &
b1 9
b0 A
1)
#200000
0)
#205000
b1 A
1)
#210000
0)
#215000
b1 $
b1 =
b0 (
b0 7
b1 %
b1 ;
b100 D
b1000000 !
b1000000 B
b0 &
b0 9
b0 A
1)
#220000
0)
#225000
b1 <
b110 "
b110 @
1)
#230000
0)
#235000
b10 <
1)
#240000
0)
#245000
b1 D
b0 %
b0 ;
b0 <
1)
#250000
0)
#255000
b1 '
b1 8
b0 $
b0 =
b10 D
1:
b0 E
b0 F
1)
#260000
0)
#265000
b1 A
1)
#270000
0)
#275000
b1 &
b1 9
b0 A
1)
#280000
0)
#285000
b1 A
1)
#290000
0)
#295000
b10 &
b10 9
b0 A
1)
#300000
0)
#305000
b1 A
1)
#310000
0)
#315000
b11 &
b11 9
b0 A
1)
#320000
0)
#325000
b1 A
1)
#330000
0)
#335000
b100 &
b100 9
b0 A
1)
#340000
0)
#345000
b1 A
1)
#350000
0)
#355000
b101 &
b101 9
b0 A
1)
#360000
0)
#365000
b1 A
1)
#370000
0)
#375000
b1 $
b1 =
b0 '
b0 8
b1 %
b1 ;
b100 D
b0 !
b0 B
b110 &
b110 9
b0 A
1)
#380000
0)
#385000
b1 <
1)
