SmartLift.v
// SmartLift.v — FPGA Elevator FSM Controller
// 8-floor elevator: floors 0–7
// Outputs: idle, door, Up, Down, current_floor, requests, max/min_request
// States: RESET → IDLE → MOVING_UP / MOVING_DOWN → DOOR_OPEN → IDLE
// Emergency stop overrides all motion

module SmartLift(
    input             clk,
    input             reset,
    input      [2:0]  req_floor,
    output reg [1:0]  idle,
    output reg [1:0]  door,
    output reg [1:0]  Up,
    output reg [1:0]  Down,
    output reg [2:0]  current_floor,
    output reg [7:0]  requests,
    output reg [2:0]  max_request,
    output reg [2:0]  min_request,
    input             emergency_stop
);

// FSM state encoding
localparam S_RESET    = 3'd0;
localparam S_IDLE     = 3'd1;
localparam S_MOVE_UP  = 3'd2;
localparam S_MOVE_DN  = 3'd3;
localparam S_DOOR     = 3'd4;
localparam S_EMERG    = 3'd5;

reg [2:0] state;

always @(posedge clk or posedge reset) begin
    if (reset) begin
        state         <= S_RESET;
        current_floor <= 3'd0;
        idle          <= 2'd1;
        door          <= 2'd0;
        Up            <= 2'd1;
        Down          <= 2'd0;
        requests      <= 8'd0;
        max_request   <= 3'd0;
        min_request   <= 3'd7;
    end
    else if (emergency_stop) begin
        state  <= S_EMERG;
        idle   <= 2'd0;
        door   <= 2'd0;
        Up     <= 2'd0;
        Down   <= 2'd0;
    end
    else begin
        case (state)
            S_RESET: begin
                state <= S_IDLE;
                idle  <= 2'd1;
            end

            S_IDLE: begin
                // Accept new floor request
                if (req_floor > current_floor) begin
                    state <= S_MOVE_UP;
                    idle  <= 2'd0;
                    door  <= 2'd0;
                    Up    <= 2'd1;
                    Down  <= 2'd0;
                end
                else if (req_floor < current_floor) begin
                    state <= S_MOVE_DN;
                    idle  <= 2'd0;
                    door  <= 2'd0;
                    Up    <= 2'd0;
                    Down  <= 2'd1;
                end
                else begin
                    // Already here — open door
                    state <= S_DOOR;
                    door  <= 2'd1;
                    idle  <= 2'd1;
                end
            end

            S_MOVE_UP: begin
                if (current_floor < req_floor)
                    current_floor <= current_floor + 1;
                else begin
                    state <= S_DOOR;
                    door  <= 2'd1;
                    Up    <= 2'd0;
                    idle  <= 2'd1;
                end
            end

            S_MOVE_DN: begin
                if (current_floor > req_floor)
                    current_floor <= current_floor - 1;
                else begin
                    state <= S_DOOR;
                    door  <= 2'd1;
                    Down  <= 2'd0;
                    idle  <= 2'd1;
                end
            end

            S_DOOR: begin
                // Door open — go back to IDLE for next request
                door  <= 2'd0;
                state <= S_IDLE;
            end

            S_EMERG: begin
                // Stay halted until reset
                idle  <= 2'd0;
                door  <= 2'd0;
            end
        endcase
    end
end

endmodule

SmartLift_Tb.v
`timescale 1ns/1ps
module SmartLift_Tb();
  reg clk=0, reset=1, emergency_stop=0;
  reg [2:0] req_floor = 0;
  wire [2:0] current_floor;
  wire [1:0] idle, door, Up, Down;
  wire [7:0] requests;
  wire [2:0] max_request, min_request;

  SmartLift dut(
    clk, reset, req_floor,
    idle, door, Up, Down,
    current_floor, requests,
    max_request, min_request, emergency_stop
  );

  initial begin
    $dumpfile("waveform.vcd");
    $dumpvars(0, SmartLift_Tb);
    #10 reset = 0;
    #5  req_floor = 3; // Request floor 3
    #80 ; // Travel time for floor 3
    #5  req_floor = 1; // Request floor 1
    #80 ; // Travel time for floor 1
    #20 $finish;
  end

  always #5 clk = ~clk; // 100MHz clock (10ns period)
endmodule

waveform.vcd
$date
	Fri Apr 24 09:18:19 2026
$end
$version
	Icarus Verilog
$end
$timescale
	1ps
$end
$scope module SmartLift_Tb $end
$var wire 8 ! requests [7:0] $end
$var wire 3 " min_request [2:0] $end
$var wire 3 # max_request [2:0] $end
$var wire 2 $ idle [1:0] $end
$var wire 2 % door [1:0] $end
$var wire 3 & current_floor [2:0] $end
$var wire 2 ' Up [1:0] $end
$var wire 2 ( Down [1:0] $end
$var reg 1 ) clk $end
$var reg 1 * emergency_stop $end
$var reg 3 + req_floor [2:0] $end
$var reg 1 , reset $end
$scope module dut $end
$var wire 1 ) clk $end
$var wire 1 * emergency_stop $end
$var wire 3 - req_floor [2:0] $end
$var wire 1 , reset $end
$var parameter 3 . S_DOOR $end
$var parameter 3 / S_EMERG $end
$var parameter 3 0 S_IDLE $end
$var parameter 3 1 S_MOVE_DN $end
$var parameter 3 2 S_MOVE_UP $end
$var parameter 3 3 S_RESET $end
$var reg 2 4 Down [1:0] $end
$var reg 2 5 Up [1:0] $end
$var reg 3 6 current_floor [2:0] $end
$var reg 2 7 door [1:0] $end
$var reg 2 8 idle [1:0] $end
$var reg 3 9 max_request [2:0] $end
$var reg 3 : min_request [2:0] $end
$var reg 8 ; requests [7:0] $end
$var reg 3 < state [2:0] $end
$upscope $end
$upscope $end
$enddefinitions $end
$comment Show the parameter values. $end
$dumpall
b0 3
b10 2
b11 1
b1 0
b101 /
b100 .
$end
#0
$dumpvars
b0 <
b0 ;
b111 :
b0 9
b1 8
b0 7
b0 6
b1 5
b0 4
b0 -
1,
b0 +
0*
0)
b0 (
b1 '
b0 &
b0 %
b1 $
b0 #
b111 "
b0 !
$end
#5000
1)
#10000
0)
0,
#15000
b1 <
1)
b11 +
b11 -
#20000
0)
#25000
b0 $
b0 8
b10 <
1)
#30000
0)
#35000
b1 &
b1 6
1)
#40000
0)
#45000
b10 &
b10 6
1)
#50000
0)
#55000
b11 &
b11 6
1)
#60000
0)
#65000
b1 $
b1 8
b0 '
b0 5
b1 %
b1 7
b100 <
1)
#70000
0)
#75000
b1 <
b0 %
b0 7
1)
#80000
0)
#85000
b1 %
b1 7
b100 <
1)
#90000
0)
#95000
b1 <
b0 %
b0 7
1)
#100000
0)
b1 +
b1 -
#105000
b1 (
b1 4
b0 $
b0 8
b11 <
1)
#110000
0)
#115000
b10 &
b10 6
1)
#120000
0)
#125000
b1 &
b1 6
1)
#130000
0)
#135000
b1 $
b1 8
b0 (
b0 4
b1 %
b1 7
b100 <
1)
#140000
0)
#145000
b1 <
b0 %
b0 7
1)
#150000
0)
#155000
b1 %
b1 7
b100 <
1)
#160000
0)
#165000
b1 <
b0 %
b0 7
1)
#170000
0)
#175000
b1 %
b1 7
b100 <
1)
#180000
0)
#185000
b1 <
b0 %
b0 7
1)
#190000
0)
#195000
b1 %
b1 7
b100 <
1)
